dash_dock/DashDock.py
dash_dock/PanelWrapper.py
dash_dock/Tab.py
dash_dock/__init__.py
dash_dock/_imports_.py
dash_dock/dash_dock.min.js
dash_dock/dash_dock.min.js.map
dash_dock/metadata.json
dash_dock/package-info.json
dash_dock-0.0.1.dist-info/LICENSE
dash_dock-0.0.1.dist-info/METADATA
dash_dock-0.0.1.dist-info/WHEEL
dash_dock-0.0.1.dist-info/top_level.txt
dash_dock-0.0.1.dist-info/RECORD
