Metadata-Version: 2.2
Name: dash_dock
Version: 0.0.1
Summary: Dynamic dock windows for dash
Author: Pip Install Python <pipinstallpython@gmail.com>
License: MIT
Classifier: Framework :: Dash
License-File: LICENSE
Dynamic: author
Dynamic: classifier
Dynamic: description
Dynamic: description-content-type
Dynamic: license
Dynamic: summary
